json_configuration/__init__.py
json_configuration/configurator.py
json_configuration-1.0.1.dist-info/METADATA
json_configuration-1.0.1.dist-info/WHEEL
json_configuration-1.0.1.dist-info/top_level.txt
json_configuration-1.0.1.dist-info/RECORD
