Metadata-Version: 2.4
Name: json-configuration
Version: 1.0.1
Requires-Dist: pydantic>=2.12.5
Dynamic: requires-dist
